{
  "id": "community/charter",
  "title": "Charter",
  "description": "Mission",
  "source": "@site/docs/community/charter.md",
  "sourceDirName": "community",
  "slug": "/community/charter",
  "permalink": "/docs/community/charter",
  "draft": false,
  "unlisted": false,
  "editUrl": "https://github.com/clearlydefined/clearlydefined/docs/community/charter.md",
  "tags": [],
  "version": "current",
  "sidebarPosition": 5,
  "frontMatter": {
    "layout": "default",
    "sidebar_position": 5,
    "title": "Charter"
  },
  "sidebar": "tutorialSidebar",
  "previous": {
    "title": "Code of Conduct",
    "permalink": "/docs/community/coc"
  },
  "next": {
    "title": "Legal",
    "permalink": "/docs/legal/"
  }
}