{
  "id": "community/meetings",
  "title": "Meetings",
  "description": "ClearlyDefined holds periodic meetings. There are two types of meetings:",
  "source": "@site/docs/community/meetings.md",
  "sourceDirName": "community",
  "slug": "/community/meetings",
  "permalink": "/docs/community/meetings",
  "draft": false,
  "unlisted": false,
  "editUrl": "https://github.com/clearlydefined/clearlydefined/docs/community/meetings.md",
  "tags": [],
  "version": "current",
  "sidebarPosition": 2,
  "frontMatter": {
    "layout": "default",
    "sidebar_position": 2,
    "title": "Meetings"
  },
  "sidebar": "tutorialSidebar",
  "previous": {
    "title": "Events",
    "permalink": "/docs/community/events"
  },
  "next": {
    "title": "Members",
    "permalink": "/docs/community/members"
  }
}